setup.cfg
setup.py
presettr/__init__.py
presettr/base.py
presettr/builder.py
presettr/decl_helpers.py
presettr/gui_creation.py
presettr/module_globals.py
presettr/patches.py
presettr/tools.py
presettr/value_items.py
presettr.egg-info/PKG-INFO
presettr.egg-info/SOURCES.txt
presettr.egg-info/dependency_links.txt
presettr.egg-info/not-zip-safe
presettr.egg-info/requires.txt
presettr.egg-info/top_level.txt