Metadata-Version: 1.0
Name: presettr
Version: 0.5.0
Summary: presettr is a layer above guidata for simplified und reusable parameter handling
Home-page: https://ssdmsource.ethz.ch/sis/pacer/tree/master
Author: Uwe Schmitt
Author-email: uwe.schmitt@id.ethz.ch
License: http://opensource.org/licenses/GPL-3.0
Platform: UNKNOWN
